maths/__init__.py
bprimal-0.0.2.dist-info/LICENSE
bprimal-0.0.2.dist-info/METADATA
bprimal-0.0.2.dist-info/WHEEL
bprimal-0.0.2.dist-info/top_level.txt
bprimal-0.0.2.dist-info/RECORD
