Metadata-Version: 2.1
Name: bprimal
Version: 0.0.2
Summary: A collection of random functions created to learn deploying a package
Home-page: https://github.com/bijeshofficial/bprimal
Author: Bijesh Raj Kunwar
Author-email: bijeshr.kunwar@gmail.com
License: UNKNOWN
Platform: UNKNOWN
Classifier: Programming Language :: Python :: 3
Classifier: License :: OSI Approved :: MIT License
Classifier: Operating System :: OS Independent
Requires-Python: >=3.6
